aws_sso_cli/__init__.py
aws_sso_cli-0.4.2.data/data/share/man/man1/aws-sso-cli.1
aws_sso_login/__init__.py
aws_sso_cli-0.4.2.dist-info/LICENSE
aws_sso_cli-0.4.2.dist-info/METADATA
aws_sso_cli-0.4.2.dist-info/WHEEL
aws_sso_cli-0.4.2.dist-info/entry_points.txt
aws_sso_cli-0.4.2.dist-info/top_level.txt
aws_sso_cli-0.4.2.dist-info/RECORD
