Metadata-Version: 2.1
Name: aws-sso-cli
Version: 0.4.2
Summary: A program to simplify logging in and setting credentials using AWS SSO.
Author: Peter Debelak
Author-email: pdebelak@gmail.com
License-File: LICENSE
Requires-Dist: boto3
Provides-Extra: dev
Requires-Dist: argparse-manpage ; extra == 'dev'
Requires-Dist: twine ; extra == 'dev'
